slack_rtm_bot/__init__.py
slack_rtm_bot/__main__.py
slack_rtm_bot/__version__.py
slack_rtm_bot/settings.py
slack_rtm_bot/settings_local.py
slack_rtm_bot/util.py
slack_rtm_bot/handlers/__init__.py
slack_rtm_bot/handlers/base.py
slack_rtm_bot/handlers/coin.py
slack_rtm_bot/handlers/dice.py
slack_rtm_bot/handlers/echo.py
slack_rtm_bot/handlers/eight_ball.py
slack_rtm_bot/handlers/help.py
slack_rtm_bot/handlers/owner.py
slack_rtm_bot/handlers/ping.py
slack_rtm_bot/handlers/reaction.py
slack_rtm_bot/handlers/rot13.py
slack_rtm_bot/handlers/tableflip.py
slack_rtm_bot/handlers/xkcd.py
slack_rtm_bot-1.0.9.dist-info/LICENSE.txt
slack_rtm_bot-1.0.9.dist-info/METADATA
slack_rtm_bot-1.0.9.dist-info/WHEEL
slack_rtm_bot-1.0.9.dist-info/entry_points.txt
slack_rtm_bot-1.0.9.dist-info/top_level.txt
slack_rtm_bot-1.0.9.dist-info/RECORD
