Metadata-Version: 2.1
Name: slack-rtm-bot
Version: 1.0.9
Summary: Slack RTM bot
Home-page: https://github.com/nkouevda/slack-rtm-bot
Author: Nikita Kouevda
Author-email: nkouevda@gmail.com
License: MIT
Platform: UNKNOWN
Requires-Dist: requests
Requires-Dist: slackclient
Requires-Dist: websocket-client
